{"mean":{"confidence_interval":{"confidence_level":0.95,"lower_bound":4389.458265086097,"upper_bound":4413.727348342056},"point_estimate":4400.7337026948635,"standard_error":6.196621995325512},"median":{"confidence_interval":{"confidence_level":0.95,"lower_bound":4376.240310077519,"upper_bound":4390.093333333333},"point_estimate":4380.744497354497,"standard_error":3.3212094595468065},"median_abs_dev":{"confidence_interval":{"confidence_level":0.95,"lower_bound":17.80763812635235,"upper_bound":34.20272453807979},"point_estimate":23.893656301523823,"standard_error":4.33460909372888},"slope":{"confidence_interval":{"confidence_level":0.95,"lower_bound":4399.271440323644,"upper_bound":4440.785121208551},"point_estimate":4418.311647268608,"standard_error":10.63903904279938},"std_dev":{"confidence_interval":{"confidence_level":0.95,"lower_bound":38.47899170502836,"upper_bound":81.65158125861407},"point_estimate":62.18076638688206,"standard_error":10.893216191893929}}